tau_log/__init__.py
tau_log/data_types.py
tau_log/log_decoder.py
tau_log-0.1.2.dist-info/LICENSE
tau_log-0.1.2.dist-info/METADATA
tau_log-0.1.2.dist-info/WHEEL
tau_log-0.1.2.dist-info/top_level.txt
tau_log-0.1.2.dist-info/RECORD
