Metadata-Version: 2.1
Name: tau-log
Version: 0.1.2
Summary: Binary log decoder for Tau project
Author-email: YuraTheBest <stuchalkin.yud@gmail.com>
Project-URL: Homepage, https://github.com/AeroKITties/tau-log
Project-URL: Issues, https://github.com/AeroKITties/tau-log/issues
Classifier: Programming Language :: Python :: 3
Classifier: License :: OSI Approved :: MIT License
Classifier: Operating System :: OS Independent
Requires-Python: >=3.8
License-File: LICENSE
